knowmine/AllSentencesExtractor.py
knowmine/FilesReader.py
knowmine/KeywordsExtractor.py
knowmine/OutputfileGenerator.py
knowmine/RelevantSentencesExtractor.py
knowmine/TextExtractor.py
knowmine/__init__.py
knowmine-0.0.5.dist-info/LICENSE
knowmine-0.0.5.dist-info/METADATA
knowmine-0.0.5.dist-info/WHEEL
knowmine-0.0.5.dist-info/top_level.txt
knowmine-0.0.5.dist-info/RECORD
