Metadata-Version: 2.1
Name: knowmine
Version: 0.0.5
Summary: Knowledge mining package
Home-page: https://github.com/GulnaraSh/knowledge-mining-python
Author: Gulnara Shavalieva
Author-email: gulsha@chalmers.se
License: UNKNOWN
Platform: UNKNOWN
Classifier: Programming Language :: Python :: 3
Classifier: License :: OSI Approved :: MIT License
Classifier: Operating System :: OS Independent
Requires-Python: >=3.0
Requires-Dist: gitpython
Requires-Dist: nltk
Requires-Dist: PyMuPDF
Requires-Dist: textract
Requires-Dist: pdfminer3
Requires-Dist: openpyxl
